mlink/__init__.py
mlink/config.py
mlink/data_stream.py
mlink/message_packer.py
mlink/mkpyevent.py
mlink-0.0.6.dist-info/METADATA
mlink-0.0.6.dist-info/WHEEL
mlink-0.0.6.dist-info/top_level.txt
mlink-0.0.6.dist-info/RECORD
