Metadata-Version: 2.1
Name: mlink
Version: 0.0.6
Summary: library for mlink
Home-page: https://makeblock.com
Author: makeblock
Author-email: flashindream@gmail.com
License: UNKNOWN
Platform: UNKNOWN
Requires-Dist: websockets (>=8.1)
